MANIFEST.in
README.rst
setup.py
minidemoKalmanFilter/__init__.py
minidemoKalmanFilter/filter.py
minidemoKalmanFilter.egg-info/PKG-INFO
minidemoKalmanFilter.egg-info/SOURCES.txt
minidemoKalmanFilter.egg-info/dependency_links.txt
minidemoKalmanFilter.egg-info/top_level.txt
minidemoKalmanFilter/examples/demo_ukf.py
minidemoKalmanFilter/examples/demo_ukf_gui.py
minidemoKalmanFilter/examples/snapshot_01.png
minidemoKalmanFilter/examples/snapshot_02.png