Metadata-Version: 1.1
Name: minidemoKalmanFilter
Version: 1.0.1
Summary: minidemoKalmanFilter - Minimal Demo. of Kalman Filters (Linear/Extended/Unscented)
Home-page: https://github.com/sken10/minidemoKalmanFilter
Author: Kenichi SHIRAKAWA
Author-email: shirakawa.kenichi@gmail.com
License: MIT License
Keywords: Kalman UKF EKF LKF
Platform: UNKNOWN
Classifier: Development Status :: 3 - Alpha
Classifier: Programming Language :: Python
Classifier: Programming Language :: Python :: 3
Classifier: Topic :: Scientific/Engineering
Classifier: Topic :: Software Development :: Libraries
